{
  "scraped_at": "2026-06-17T12:46:03.196159+00:00",
  "source": "streamscharts.com",
  "period": "last_7_days",
  "channels": [
    {
      "rank": 1,
      "name": "absi",
      "slug": "absi",
      "url": "https://kick.com/absi",
      "avatar": "https://cdnr.escharts.com/channels/78/id/26869410",
      "country": "Jordan",
      "country_code": "JO",
      "language": "AR",
      "primary_game": "IRL",
      "primary_game_slug": "irl",
      "followers": 801255,
      "followers_compact": "801K",
      "hours_watched": 6432856,
      "peak_viewers": 52518,
      "average_viewers": 38695,
      "airtime_minutes": 9975,
      "airtime_display": "166h 15m",
      "followers_gained": 5216
    },
    {
      "rank": 2,
      "name": "odablock",
      "slug": "odablock",
      "url": "https://kick.com/odablock",
      "avatar": "https://cdnr.escharts.com/channels/78/id/2401072?width=56&height=56",
      "country": "USA",
      "country_code": "US",
      "language": "EN",
      "primary_game": "Old School RuneScape",
      "primary_game_slug": "old-school-runescape",
      "followers": 262898,
      "followers_compact": "263K",
      "hours_watched": 3049747,
      "peak_viewers": 57482,
      "average_viewers": 36671,
      "airtime_minutes": 4990,
      "airtime_display": "83h 10m",
      "followers_gained": 5596
    },
    {
      "rank": 3,
      "name": "jonvlogs",
      "slug": "jonvlogs",
      "url": "https://kick.com/jonvlogs",
      "avatar": "https://cdnr.escharts.com/channels/78/id/88374155",
      "country": "Brazil",
      "country_code": "BR",
      "language": "PT",
      "primary_game": "IRL",
      "primary_game_slug": "irl",
      "followers": 84621,
      "followers_compact": "85K",
      "hours_watched": 2242861,
      "peak_viewers": 25192,
      "average_viewers": 13358,
      "airtime_minutes": 10075,
      "airtime_display": "167h 55m",
      "followers_gained": 14828
    },
    {
      "rank": 4,
      "name": "solomission",
      "slug": "solomission",
      "url": "https://kick.com/solomission",
      "avatar": "https://cdnr.escharts.com/channels/78/id/2226449?width=56&height=56",
      "country": null,
      "country_code": null,
      "language": "EN",
      "primary_game": "Old School RuneScape",
      "primary_game_slug": "old-school-runescape",
      "followers": 30027,
      "followers_compact": "30K",
      "hours_watched": 2030649,
      "peak_viewers": 45724,
      "average_viewers": 23033,
      "airtime_minutes": 5290,
      "airtime_display": "88h 10m",
      "followers_gained": 12713
    },
    {
      "rank": 5,
      "name": "deenthegreat",
      "slug": "deenthegreat",
      "url": "https://kick.com/deenthegreat",
      "avatar": "https://cdnr.escharts.com/channels/78/id/5417122",
      "country": null,
      "country_code": null,
      "language": "EN",
      "primary_game": "IRL",
      "primary_game_slug": "irl",
      "followers": 215439,
      "followers_compact": "215K",
      "hours_watched": 1964638,
      "peak_viewers": 41499,
      "average_viewers": 11701,
      "airtime_minutes": 10075,
      "airtime_display": "167h 55m",
      "followers_gained": 26644
    },
    {
      "rank": 6,
      "name": "maherco",
      "slug": "maherco",
      "url": "https://kick.com/maherco",
      "avatar": "https://cdnr.escharts.com/channels/78/id/11853347?width=56&height=56",
      "country": null,
      "country_code": null,
      "language": "AR",
      "primary_game": "Just Chatting",
      "primary_game_slug": "just-chatting",
      "followers": 705747,
      "followers_compact": "706K",
      "hours_watched": 1733934,
      "peak_viewers": 47619,
      "average_viewers": 31056,
      "airtime_minutes": 3350,
      "airtime_display": "55h 50m",
      "followers_gained": 11911
    },
    {
      "rank": 7,
      "name": "lacobraaa",
      "slug": "lacobraaa",
      "url": "https://kick.com/lacobraaa",
      "avatar": "https://cdnr.escharts.com/channels/78/id/30376205?width=56&height=56",
      "country": null,
      "country_code": null,
      "language": "ES",
      "primary_game": "Just Chatting",
      "primary_game_slug": "just-chatting",
      "followers": 1596234,
      "followers_compact": "1.60M",
      "hours_watched": 1669175,
      "peak_viewers": 89197,
      "average_viewers": 23077,
      "airtime_minutes": 4340,
      "airtime_display": "72h 20m",
      "followers_gained": 49302
    },
    {
      "rank": 8,
      "name": "oilrats",
      "slug": "oilrats",
      "url": "https://kick.com/oilrats",
      "avatar": "https://cdnr.escharts.com/channels/78/id/109579",
      "country": null,
      "country_code": null,
      "language": "EN",
      "primary_game": "Rust",
      "primary_game_slug": "rust",
      "followers": 74665,
      "followers_compact": "75K",
      "hours_watched": 1535416,
      "peak_viewers": 51513,
      "average_viewers": 12442,
      "airtime_minutes": 7405,
      "airtime_display": "123h 25m",
      "followers_gained": 19250
    },
    {
      "rank": 9,
      "name": "sxb",
      "slug": "sxb",
      "url": "https://kick.com/sxb",
      "avatar": "https://cdnr.escharts.com/channels/78/id/17883767?width=56&height=56",
      "country": null,
      "country_code": null,
      "language": "AR",
      "primary_game": "Grand Theft Auto V (GTA)",
      "primary_game_slug": "grand-theft-auto-v-gta",
      "followers": 1690446,
      "followers_compact": "1.69M",
      "hours_watched": 1494441,
      "peak_viewers": 133889,
      "average_viewers": 85806,
      "airtime_minutes": 1045,
      "airtime_display": "17h 25m",
      "followers_gained": 21198
    },
    {
      "rank": 10,
      "name": "forg1",
      "slug": "forg1",
      "url": "https://kick.com/forg1",
      "avatar": "https://cdnr.escharts.com/channels/78/id/11505116?width=56&height=56",
      "country": null,
      "country_code": null,
      "language": "ES",
      "primary_game": "Counter-Strike 2",
      "primary_game_slug": "counter-strike-2",
      "followers": 99307,
      "followers_compact": "99K",
      "hours_watched": 1419328,
      "peak_viewers": 101768,
      "average_viewers": 23365,
      "airtime_minutes": 3645,
      "airtime_display": "60h 45m",
      "followers_gained": 20201
    },
    {
      "rank": 11,
      "name": "panpots",
      "slug": "panpots",
      "url": "https://kick.com/panpots",
      "avatar": "https://cdnr.escharts.com/channels/78/id/6357957",
      "country": null,
      "country_code": null,
      "language": "ES",
      "primary_game": "Rust",
      "primary_game_slug": "rust",
      "followers": 46504,
      "followers_compact": "47K",
      "hours_watched": 1288957,
      "peak_viewers": 50387,
      "average_viewers": 10150,
      "airtime_minutes": 7620,
      "airtime_display": "127h",
      "followers_gained": 11002
    },
    {
      "rank": 12,
      "name": "krolay",
      "slug": "krolay",
      "url": "https://kick.com/krolay",
      "avatar": "https://cdnr.escharts.com/channels/78/id/413399",
      "country": null,
      "country_code": null,
      "language": "FR",
      "primary_game": "Rust",
      "primary_game_slug": "rust",
      "followers": 21498,
      "followers_compact": "21K",
      "hours_watched": 1268987,
      "peak_viewers": 52226,
      "average_viewers": 8948,
      "airtime_minutes": 8510,
      "airtime_display": "141h 50m",
      "followers_gained": 18033
    },
    {
      "rank": 13,
      "name": "hjune",
      "slug": "hjune",
      "url": "https://kick.com/hjune",
      "avatar": "https://cdnr.escharts.com/channels/78/id/95355",
      "country": null,
      "country_code": null,
      "language": "EN",
      "primary_game": "Rust",
      "primary_game_slug": "rust",
      "followers": 48175,
      "followers_compact": "48K",
      "hours_watched": 1202670,
      "peak_viewers": 42354,
      "average_viewers": 9508,
      "airtime_minutes": 7590,
      "airtime_display": "126h 30m",
      "followers_gained": 16614
    },
    {
      "rank": 14,
      "name": "sinks",
      "slug": "sinks",
      "url": "https://kick.com/sinks",
      "avatar": "https://cdnr.escharts.com/channels/78/id/62294",
      "country": null,
      "country_code": null,
      "language": "EN",
      "primary_game": "Rust",
      "primary_game_slug": "rust",
      "followers": 14571,
      "followers_compact": "15K",
      "hours_watched": 1150145,
      "peak_viewers": 44876,
      "average_viewers": 9233,
      "airtime_minutes": 7475,
      "airtime_display": "124h 35m",
      "followers_gained": 12836
    },
    {
      "rank": 15,
      "name": "davooxeneize",
      "slug": "davooxeneize",
      "url": "https://kick.com/davooxeneize",
      "avatar": "https://cdnr.escharts.com/channels/78/id/30204909?width=56&height=56",
      "country": null,
      "country_code": null,
      "language": "ES",
      "primary_game": "Just Chatting",
      "primary_game_slug": "just-chatting",
      "followers": 1843932,
      "followers_compact": "1.84M",
      "hours_watched": 1127311,
      "peak_viewers": 63891,
      "average_viewers": 25429,
      "airtime_minutes": 2660,
      "airtime_display": "44h 20m",
      "followers_gained": 18651
    },
    {
      "rank": 16,
      "name": "roshtein",
      "slug": "roshtein",
      "url": "https://kick.com/roshtein",
      "avatar": "https://cdnr.escharts.com/channels/78/id/4599",
      "country": null,
      "country_code": null,
      "language": "EN",
      "primary_game": "Slots &amp; Casino",
      "primary_game_slug": "slots-casino",
      "followers": 394693,
      "followers_compact": "395K",
      "hours_watched": 1124424,
      "peak_viewers": 21621,
      "average_viewers": 15564,
      "airtime_minutes": 4335,
      "airtime_display": "72h 15m",
      "followers_gained": 2672
    },
    {
      "rank": 17,
      "name": "coringa",
      "slug": "coringa",
      "url": "https://kick.com/coringa",
      "avatar": "https://cdnr.escharts.com/channels/78/id/4124791?width=56&height=56",
      "country": null,
      "country_code": null,
      "language": "PT",
      "primary_game": "IRL",
      "primary_game_slug": "irl",
      "followers": 410736,
      "followers_compact": "411K",
      "hours_watched": 1093575,
      "peak_viewers": 51680,
      "average_viewers": 18775,
      "airtime_minutes": 3495,
      "airtime_display": "58h 15m",
      "followers_gained": 29084
    },
    {
      "rank": 18,
      "name": "westcol",
      "slug": "westcol",
      "url": "https://kick.com/westcol",
      "avatar": "https://cdnr.escharts.com/channels/78/id/669746?width=56&height=56",
      "country": null,
      "country_code": null,
      "language": "ES",
      "primary_game": "IRL",
      "primary_game_slug": "irl",
      "followers": 3961572,
      "followers_compact": "3.96M",
      "hours_watched": 1053934,
      "peak_viewers": 76359,
      "average_viewers": 36981,
      "airtime_minutes": 1710,
      "airtime_display": "28h 30m",
      "followers_gained": 11685
    },
    {
      "rank": 19,
      "name": "eray",
      "slug": "eray",
      "url": "https://kick.com/eray",
      "avatar": "https://cdnr.escharts.com/channels/78/id/10337013?width=56&height=56",
      "country": null,
      "country_code": null,
      "language": "TR",
      "primary_game": "Grand Theft Auto V (GTA)",
      "primary_game_slug": "grand-theft-auto-v-gta",
      "followers": 717051,
      "followers_compact": "717K",
      "hours_watched": 1010698,
      "peak_viewers": 105860,
      "average_viewers": 20733,
      "airtime_minutes": 2925,
      "airtime_display": "48h 45m",
      "followers_gained": 4827
    },
    {
      "rank": 20,
      "name": "ricoy",
      "slug": "ricoy",
      "url": "https://kick.com/ricoy",
      "avatar": "https://cdnr.escharts.com/channels/78/id/1661881",
      "country": null,
      "country_code": null,
      "language": "ES",
      "primary_game": "Rust",
      "primary_game_slug": "rust",
      "followers": 72312,
      "followers_compact": "72K",
      "hours_watched": 931335,
      "peak_viewers": 33200,
      "average_viewers": 7330,
      "airtime_minutes": 7625,
      "airtime_display": "127h 5m",
      "followers_gained": 12524
    }
  ]
}